RGBMatrixEmulator/__init__.py
RGBMatrixEmulator/icon.png
RGBMatrixEmulator/logger.py
RGBMatrixEmulator/version.py
RGBMatrixEmulator/adapters/__init__.py
RGBMatrixEmulator/adapters/base.py
RGBMatrixEmulator/adapters/pygame_adapter.py
RGBMatrixEmulator/adapters/sixel_adapter.py
RGBMatrixEmulator/adapters/terminal_adapter.py
RGBMatrixEmulator/adapters/tkinter_adapter.py
RGBMatrixEmulator/adapters/turtle_adapter.py
RGBMatrixEmulator/adapters/browser_adapter/README.md
RGBMatrixEmulator/adapters/browser_adapter/__init__.py
RGBMatrixEmulator/adapters/browser_adapter/adapter.py
RGBMatrixEmulator/adapters/browser_adapter/fps.py
RGBMatrixEmulator/adapters/browser_adapter/server.py
RGBMatrixEmulator/adapters/browser_adapter/request_handlers/__init__.py
RGBMatrixEmulator/adapters/browser_adapter/request_handlers/base.py
RGBMatrixEmulator/adapters/browser_adapter/request_handlers/image.py
RGBMatrixEmulator/adapters/browser_adapter/request_handlers/image_web_socket.py
RGBMatrixEmulator/adapters/browser_adapter/request_handlers/main.py
RGBMatrixEmulator/adapters/browser_adapter/request_handlers/single_file.py
RGBMatrixEmulator/adapters/browser_adapter/static/index.html
RGBMatrixEmulator/adapters/browser_adapter/static/assets/client.js
RGBMatrixEmulator/adapters/browser_adapter/static/assets/icon.ico
RGBMatrixEmulator/adapters/browser_adapter/static/assets/styles.css
RGBMatrixEmulator/adapters/pi5_adapter/README.md
RGBMatrixEmulator/adapters/pi5_adapter/__init__.py
RGBMatrixEmulator/adapters/raw_adapter/README.md
RGBMatrixEmulator/adapters/raw_adapter/__init__.py
RGBMatrixEmulator/emulation/__init__.py
RGBMatrixEmulator/emulation/canvas.py
RGBMatrixEmulator/emulation/matrix.py
RGBMatrixEmulator/emulation/options.py
RGBMatrixEmulator/graphics/__init__.py
RGBMatrixEmulator/graphics/color.py
RGBMatrixEmulator/graphics/font.py
rgbmatrixemulator-0.15.1.data/data/RGBMatrixEmulator/client.js
rgbmatrixemulator-0.15.1.data/data/RGBMatrixEmulator/icon.ico
rgbmatrixemulator-0.15.1.dist-info/METADATA
rgbmatrixemulator-0.15.1.dist-info/WHEEL
rgbmatrixemulator-0.15.1.dist-info/licenses/LICENSE
rgbmatrixemulator-0.15.1.dist-info/RECORD
