Metadata-Version: 2.4
Name: RGBMatrixEmulator
Version: 0.15.1
Summary: A PC emulator for Raspberry Pi LED matrices driven by rpi-rgb-led-matrix
Project-URL: Homepage, https://github.com/ty-porter/RGBMatrixEmulator
Author-email: Tyler Porter <tyler.b.porter@gmail.com>
License-Expression: MIT
License-File: LICENSE
Keywords: LED,LED matrix,RPI,matrix,raspberry,raspberry pi
Classifier: Development Status :: 4 - Beta
Classifier: Environment :: Console
Classifier: Intended Audience :: Developers
Classifier: Intended Audience :: Other Audience
Classifier: License :: OSI Approved :: MIT License
Classifier: Natural Language :: English
Classifier: Operating System :: OS Independent
Classifier: Programming Language :: Python :: 3
Classifier: Topic :: Other/Nonlisted Topic
Requires-Dist: bdfparser<=2.2.0
Requires-Dist: libsixel-python>=0.5.0
Requires-Dist: numpy>=1.2.0
Requires-Dist: pillow>=10.0.1
Requires-Dist: pygame<3,>=2.0.1
Requires-Dist: tornado>=6.1
Provides-Extra: pi5
Requires-Dist: adafruit-blinka-raspberry-pi5-piomatter>=1.0.0; extra == 'pi5'
Requires-Dist: adafruit-blinka>=8.0.0; extra == 'pi5'
